unixdump/__init__.py
unixdump/screen.py
unixdump/session.py
unixdump/term_screen_wayland.py
unixdump/term_screen_x11.py
unixdump/term_tmux_wayland.py
unixdump/term_tmux_x11.py
unixdump/term_wayland.py
unixdump/term_x11.py
unixdump/tmux.py
unixdump/ud2b.py
unixdump-1.2.0.dist-info/LICENSE
unixdump-1.2.0.dist-info/METADATA
unixdump-1.2.0.dist-info/WHEEL
unixdump-1.2.0.dist-info/entry_points.txt
unixdump-1.2.0.dist-info/top_level.txt
unixdump-1.2.0.dist-info/RECORD
