Metadata-Version: 2.1
Name: unixdump
Version: 1.2.0
Summary: eBPF-based namespace-agnostic tcpdump-alike for Unix domain sockets
Home-page: https://github.com/nccgroup/ebpf
Author: Andy Olsen, Jeff Dileo
Author-email: andy.olsen@nccgroup.com, jeff.dileo@nccgroup.com
License: GPLv2 (Only)/BSD (2 Clause)
Keywords: unixdump packet capture pcap unix domain sockets tcpdump ebpf
Platform: UNKNOWN
Classifier: License :: OSI Approved :: GNU General Public License v2 (GPLv2)
Classifier: License :: OSI Approved :: BSD License
Classifier: Programming Language :: Python :: 3.5
Classifier: Operating System :: POSIX :: Linux
Classifier: Topic :: System :: Networking :: Monitoring
Classifier: Topic :: System :: Operating System Kernels :: Linux
Classifier: Topic :: Security
Requires-Python: >=3.5.0
License-File: ../LICENSE
Requires-Dist: pybst (<2,>=1.0)
Requires-Dist: hexdump (<4,>=3.3)
Requires-Dist: uninstallable (>0) ; platform_system != "Linux"
